setup.py
pyspreedly/__init__.py
pyspreedly/api.py
pyspreedly/objectify.py
pyspreedly.egg-info/PKG-INFO
pyspreedly.egg-info/SOURCES.txt
pyspreedly.egg-info/dependency_links.txt
pyspreedly.egg-info/not-zip-safe
pyspreedly.egg-info/requires.txt
pyspreedly.egg-info/top_level.txt
pyspreedly/test/__init__.py
pyspreedly/test/runtests.py
pyspreedly/test/site_conf.py
pyspreedly/test/test.py