Metadata-Version: 1.1
Name: pyspreedly
Version: 2.0.1
Summary: API for spreedly
Home-page: http://github.org/mediapop/python-spreedly
Author: MediaPop
Author-email: dev@mediapop.co
License: UNKNOWN
Platform: UNKNOWN
Classifier: Intended Audience :: Developers
Classifier: Intended Audience :: System Administrators
Classifier: Operating System :: OS Independent
Classifier: Programming Language :: Python
Classifier: License :: OSI Approved :: MIT License
Classifier: Topic :: Software Development :: Libraries :: Python Modules
